pyDCFV/__init__.py
pyDCFV/dcf.py
pydcfv-1.0.dist-info/LICENSE
pydcfv-1.0.dist-info/WHEEL
pydcfv-1.0.dist-info/METADATA
pydcfv-1.0.dist-info/RECORD
