Metadata-Version: 2.1
Name: pyDCFV
Version: 1.0
Summary: An amazing sample package!
Author-email: Jack Klingenberg <work.jackklingenberg1@gmail.com>
Classifier: License :: OSI Approved :: MIT License
Project-URL: Home, https://github.com/Jack-Klingenberg/pyDCF
